svgchecklib/__init__.py
svgchecklib/svgchecklib.py
svgchecklib/word_properties.py
py_svgcheck_lib-0.0.1.dist-info/METADATA
py_svgcheck_lib-0.0.1.dist-info/WHEEL
py_svgcheck_lib-0.0.1.dist-info/top_level.txt
py_svgcheck_lib-0.0.1.dist-info/RECORD
