Metadata-Version: 2.1
Name: py_svgcheck_lib
Version: 0.0.1
Summary: Python Library for SVG Validation (fork of the svgcheck cli)
Home-page: https://github.com/anton-yablonovsky/svgchecklib.git
Author: Anton Yablonovsky
Author-email: anton.yablonovsky@gmail.com
Classifier: Programming Language :: Python :: 3
Classifier: License :: OSI Approved :: MIT License
Classifier: Operating System :: OS Independent
Requires-Python: >=3.6
Requires-Dist: lxml
Requires-Dist: xml2rfc
